setup.py
otterop/io/console.py
otterop_io-0.2.0.dist-info/METADATA
otterop_io-0.2.0.dist-info/WHEEL
otterop_io-0.2.0.dist-info/RECORD
