Metadata-Version: 2.1
Name: otterop-io
Version: 0.2.0
Summary: OtterOP io
Author-email: Emanuele Sabellico <emasab@gmail.com>
Requires-Python: >=3.7
Requires-Dist: otterop-lang>=0.2.0
